vmipy/__init__.py
vmipy/gforce/__init__.py
vmipy/gforce/gforce.py
vmipy/ohand/__init__.py
vmipy/ohand/ohand.py
vmipy/vmi485tousb/__init__.py
vmipy/vmi485tousb/_uartChannel.py
vmipy/vmichannel/__init__.py
vmipy/vmichannel/_mqttchannel.py
vmipy/vmichannel/_websocketChannel.py
vmipy/vmiconfig/__init__.py
vmipy/vmiconfig/_config.py
vmipy/vmidevice/__init__.py
vmipy/vmidevice/_abstract.py
vmipy/vmidevice/_wsdevice.py
vmipy/vmidevice/launch.py
vmipy/vmiiputil/__init__.py
vmipy/vmiiputil/_iputil.py
vmipy/vmilog/__init__.py
vmipy/vmilog/_logging.py
vmipy/vmimpeg/__init__.py
vmipy/vmimpeg/_stream.py
vmipy-25.9.17.dist-info/licenses/LICENSE
vmipy-25.9.17.dist-info/METADATA
vmipy-25.9.17.dist-info/WHEEL
vmipy-25.9.17.dist-info/top_level.txt
vmipy-25.9.17.dist-info/RECORD
